LangSegment/LangSegment.py
LangSegment/__init__.py
LangSegment/utils/__init__.py
LangSegment/utils/num.py
LangSegment-0.3.5.dist-info/METADATA
LangSegment-0.3.5.dist-info/WHEEL
LangSegment-0.3.5.dist-info/top_level.txt
LangSegment-0.3.5.dist-info/RECORD
